./LICENSE
./PKG-INFO
./README.md
./__init__.py
./pyproject.toml
./serfilesreader.py
serfilesreader-0.0.8.dist-info/METADATA
serfilesreader-0.0.8.dist-info/WHEEL
serfilesreader-0.0.8.dist-info/licenses/LICENSE
serfilesreader-0.0.8.dist-info/RECORD
