Metadata-Version: 2.1
Name: serfilesreader
Version: 0.0.8
Summary: A library handling SER files
Project-URL: Homepage, https://gitlab.com/ashashiwa/pyserfilesreader
Author-email: JB BUTET <ashashiwa@gmail.com>
License-File: LICENSE
Classifier: License :: OSI Approved :: GNU Lesser General Public License v3 or later (LGPLv3+)
Classifier: Operating System :: OS Independent
Classifier: Programming Language :: Python :: 3
Requires-Python: >=3.8
